conditions_ai/__init__.py
conditions_ai/constants/__init__.py
conditions_ai/constants/prompts.py
conditions_ai/models/__init__.py
conditions_ai/models/conditions_openai.py
conditions_ai/utils/__init__.py
conditions_ai/utils/bool_converter.py
conditions_ai-0.1.3.dist-info/LICENSE
conditions_ai-0.1.3.dist-info/METADATA
conditions_ai-0.1.3.dist-info/WHEEL
conditions_ai-0.1.3.dist-info/top_level.txt
conditions_ai-0.1.3.dist-info/RECORD
