Metadata-Version: 2.1
Name: conditions-ai
Version: 0.1.3
Summary: Harness the true power of 🚀GenAI🚀
Requires-Python: >=3.8
License-File: LICENSE
Requires-Dist: loguru >=0.7.2
Requires-Dist: openai >=1.52.2
Requires-Dist: python-dotenv >=1.0.1
